arr_deal/__init__.py
arr_deal/search.py
arr_deal/sort.py
arr_deal-0.0.3.dist-info/METADATA
arr_deal-0.0.3.dist-info/WHEEL
arr_deal-0.0.3.dist-info/top_level.txt
arr_deal-0.0.3.dist-info/RECORD
