Metadata-Version: 2.1
Name: arr-deal
Version: 0.0.3
Summary: Just a small effort
Home-page: https://github.com/urplatshubham/arr_deal
Author: Shubham Rajak
License: UNKNOWN
Platform: UNKNOWN
Classifier: Programming Language :: Python :: 3
Classifier: Operating System :: OS Independent
Requires-Python: >=3.6
